setup.py
src/inlinestyle/__init__.py
src/inlinestyle/soupselect.py
src/inlinestyle.egg-info/PKG-INFO
src/inlinestyle.egg-info/SOURCES.txt
src/inlinestyle.egg-info/dependency_links.txt
src/inlinestyle.egg-info/requires.txt
src/inlinestyle.egg-info/top_level.txt