Metadata-Version: 1.0
Name: inlinestyle
Version: 0.3
Summary: convert html style blocks to inline style statements
Home-page: https://github.com/binarydud/inlinestyler
Author: Matt George
Author-email: mgeorge@gmail.com
License: UNKNOWN
Platform: UNKNOWN
